gemini_all_for_one/__init__.py
gemini_all_for_one/api/__init__.py
gemini_all_for_one/api/flask_app.py
gemini_all_for_one/core/__init__.py
gemini_all_for_one/core/gemini_chat.py
gemini_all_for_one/core/image_analysis.py
gemini_all_for_one/core/image_editing.py
gemini_all_for_one/core/image_generation.py
gemini_all_for_one/core/pollinations_client.py
gemini_all_for_one/core/simple_gemini.py
gemini_all_for_one/templates/__init__.py
gemini_all_for_one/templates/docs.html
gemini_all_for_one/templates/index.html
gemini_all_for_one-1.0.2.dist-info/licenses/LICENSE
gemini_all_for_one-1.0.2.dist-info/METADATA
gemini_all_for_one-1.0.2.dist-info/WHEEL
gemini_all_for_one-1.0.2.dist-info/entry_points.txt
gemini_all_for_one-1.0.2.dist-info/top_level.txt
gemini_all_for_one-1.0.2.dist-info/RECORD
