Metadata-Version: 2.4
Name: gemini-all-for-one
Version: 1.0.2
Summary: A comprehensive AI image platform powered by Google's Gemini AI
Home-page: https://github.com/ai-image-platform/gemini-all-for-one
Author: AI Image Platform Team
Author-email: support@ai-image-platform.com
Project-URL: Bug Reports, https://github.com/ai-image-platform/gemini-all-for-one/issues
Project-URL: Source, https://github.com/ai-image-platform/gemini-all-for-one
Project-URL: Documentation, https://gemini-all-for-one.readthedocs.io/
Keywords: ai artificial-intelligence image-generation image-analysis image-editing gemini google multimodal chat
Classifier: Development Status :: 5 - Production/Stable
Classifier: Intended Audience :: Developers
Classifier: License :: OSI Approved :: MIT License
Classifier: Operating System :: OS Independent
Classifier: Programming Language :: Python :: 3
Classifier: Programming Language :: Python :: 3.8
Classifier: Programming Language :: Python :: 3.9
Classifier: Programming Language :: Python :: 3.10
Classifier: Programming Language :: Python :: 3.11
Classifier: Programming Language :: Python :: 3.12
Classifier: Topic :: Scientific/Engineering :: Artificial Intelligence
Classifier: Topic :: Software Development :: Libraries :: Python Modules
Classifier: Topic :: Multimedia :: Graphics :: Graphics Conversion
Requires-Python: >=3.8
License-File: LICENSE
Requires-Dist: flask>=2.3.0
Requires-Dist: google-genai>=1.33.0
Requires-Dist: google-generativeai>=0.8.5
Requires-Dist: pillow>=10.0.0
Requires-Dist: requests>=2.31.0
Requires-Dist: werkzeug>=2.3.0
Provides-Extra: dev
Requires-Dist: pytest>=7.0.0; extra == "dev"
Requires-Dist: black>=23.0.0; extra == "dev"
Requires-Dist: flake8>=6.0.0; extra == "dev"
Requires-Dist: mypy>=1.0.0; extra == "dev"
Provides-Extra: docs
Requires-Dist: sphinx>=6.0.0; extra == "docs"
Requires-Dist: sphinx-rtd-theme>=1.2.0; extra == "docs"
Dynamic: author
Dynamic: author-email
Dynamic: classifier
Dynamic: description
Dynamic: description-content-type
Dynamic: home-page
Dynamic: keywords
Dynamic: license-file
Dynamic: project-url
Dynamic: provides-extra
Dynamic: requires-dist
Dynamic: requires-python
Dynamic: summary
